bandit_sarif_formatter/__init__.py
bandit_sarif_formatter/formatter.py
bandit_sarif_formatter/sarif_object_model.py
bandit_sarif_formatter/serialization.py
bandit_sarif_formatter-1.1.1.dist-info/AUTHORS
bandit_sarif_formatter-1.1.1.dist-info/LICENSE
bandit_sarif_formatter-1.1.1.dist-info/METADATA
bandit_sarif_formatter-1.1.1.dist-info/WHEEL
bandit_sarif_formatter-1.1.1.dist-info/entry_points.txt
bandit_sarif_formatter-1.1.1.dist-info/pbr.json
bandit_sarif_formatter-1.1.1.dist-info/top_level.txt
bandit_sarif_formatter-1.1.1.dist-info/RECORD
