Metadata-Version: 2.1
Name: bandit-sarif-formatter
Version: 1.1.1
Summary: A Bandit formatter for the Static Analysis Results Interchange Format (SARIF) Version 2.1.0 file format.
Home-page: https://github.com/microsoft/bandit-sarif-formatter
Author: Microsoft Corporation
Author-email: v-lgold@microsoft.com
License: MIT
Platform: UNKNOWN
Classifier: Development Status :: 5 - Production/Stable
Classifier: Environment :: Console
Classifier: Intended Audience :: Developers
Classifier: Intended Audience :: Information Technology
Classifier: License :: OSI Approved :: MIT License
Classifier: Operating System :: OS Independent
Classifier: Programming Language :: Python
Requires-Python: >= 2.7
Requires-Dist: jschema-to-python (>=1.2.3)
Requires-Dist: sarif-om (>=1.0.4)
